_examples/__init__.py
examples/__init__.py
tests/__init__.py
tests/base.py
tests/test_log.py
tests/test_portfolio.py
tests/test_winsorize.py
transforms_fin/__init__.py
transforms_fin/log.py
transforms_fin/portfolio.py
transforms_fin/winsorize.py
transforms_fin-0.1.2.dist-info/LICENSE.md
transforms_fin-0.1.2.dist-info/METADATA
transforms_fin-0.1.2.dist-info/WHEEL
transforms_fin-0.1.2.dist-info/entry_points.txt
transforms_fin-0.1.2.dist-info/top_level.txt
transforms_fin-0.1.2.dist-info/RECORD
