Metadata-Version: 2.1
Name: transforms-fin
Version: 0.1.2
Summary: A set of Transforms meant for financial analysis to be used with the datacode package
Home-page: https://github.com/nickderobertis/transforms-fin
Author: Nick DeRobertis
Author-email: whoopnip@gmail.com
License: MIT
Project-URL: Code, https://github.com/nickderobertis/transforms-fin
Project-URL: Documentation, https://nickderobertis.github.io/transforms-fin
Platform: UNKNOWN
Classifier: Development Status :: 3 - Alpha
Classifier: Intended Audience :: Developers
Classifier: Programming Language :: Python :: 3.6
Classifier: Programming Language :: Python :: 3.7
Requires-Dist: datacode
Requires-Dist: pd-utils
